twh_download/__init__.py
twh_download/__main__.py
twh_download/cli.py
twh_download/config.toml
twh_download/export.py
troopwebhost_download-0.3.3.dist-info/METADATA
troopwebhost_download-0.3.3.dist-info/WHEEL
troopwebhost_download-0.3.3.dist-info/entry_points.txt
troopwebhost_download-0.3.3.dist-info/licenses/LICENSE
troopwebhost_download-0.3.3.dist-info/RECORD
