Metadata-Version: 2.1
Name: troopwebhost-download
Version: 0.3.3
Summary: Retrieve CSV files from Troopwebhost
Author-email: Michael Perkins <perkinsms@gmail.com>
Maintainer-email: Michael Perkins <perkinsms@gmail.com>
License: MIT License
License-File: LICENSE
Classifier: Development Status :: 4 - Beta
Classifier: License :: OSI Approved :: MIT License
Classifier: Programming Language :: Python :: 3
Classifier: Programming Language :: Python :: 3.9
Classifier: Programming Language :: Python :: 3.10
Classifier: Programming Language :: Python :: 3.11
Requires-Python: >3.9
Requires-Dist: python-dotenv
Requires-Dist: requests
Requires-Dist: toml~=0.10
